LICENSE.txt
MANIFEST.in
README.rst
setup.py
bdvisual/__init__.py
bdvisual/plot/__init__.py
bdvisual/plot/combination.py
bdvisual/plot/outdir.py
bdvisual/plot/rador.py
big_data_visual.egg-info/PKG-INFO
big_data_visual.egg-info/SOURCES.txt
big_data_visual.egg-info/dependency_links.txt
big_data_visual.egg-info/requires.txt
big_data_visual.egg-info/top_level.txt